zenroom/__init__.py
zenroom/__main__.py
zenroom/kernel.py
jupyter_zenroom_kernel-0.0.8.dist-info/LICENSE
jupyter_zenroom_kernel-0.0.8.dist-info/METADATA
jupyter_zenroom_kernel-0.0.8.dist-info/WHEEL
jupyter_zenroom_kernel-0.0.8.dist-info/top_level.txt
jupyter_zenroom_kernel-0.0.8.dist-info/RECORD
