Metadata-Version: 2.1
Name: jupyter-zenroom-kernel
Version: 0.0.8
Summary: Jupyter kernel for Zenroom. Small, secure and portable virtual machine for crypto language processing
Home-page: https://github.com/puria/jupyter-zenroom-kernel
Author: Dyne Development Team
Author-email: puria@dyne.org
License: AGPLv3+
Project-URL: Zenroom project, https://zenroom.dyne.org/
Project-URL: Decode Project, https://decodeproject.eu/
Project-URL: Tracker, https://github.com/puria/jupyter-zenroom-kernel/issues
Platform: Linux
Platform: Mac OS X
Platform: Windows
Classifier: Framework :: Jupyter
Classifier: Intended Audience :: Developers
Classifier: Intended Audience :: Science/Research
Classifier: Intended Audience :: End Users/Desktop
Classifier: License :: OSI Approved :: GNU Affero General Public License v3
Classifier: Programming Language :: Python :: 3
Classifier: Topic :: Security :: Cryptography
Classifier: Topic :: System :: Distributed Computing
Requires-Python: >=3
Requires-Dist: metakernel (==0.20.14)
Requires-Dist: notebook (>=5.4.1)
Requires-Dist: html2text
Provides-Extra: test
Requires-Dist: coverage; extra == 'test'
Requires-Dist: nose; extra == 'test'
Requires-Dist: jupyter-kernel-test; extra == 'test'
